setup.py
Heractor.egg-info/PKG-INFO
Heractor.egg-info/SOURCES.txt
Heractor.egg-info/dependency_links.txt
Heractor.egg-info/entry_points.txt
Heractor.egg-info/requires.txt
Heractor.egg-info/top_level.txt
heractor/__init__.py
heractor/commands.py
heractor/heract.py
heractor/plugins/__init__.py
heractor/plugins/blog.py
heractor/plugins/breadcrumbs.py
heractor/plugins/buildmenu.py
heractor/plugins/include.py
heractor/plugins/listviewdetail.py
heractor/plugins/markdn.py
heractor/plugins/paginator.py
heractor/plugins/structure.py