Metadata-Version: 1.0
Name: Heractor
Version: 1.05
Summary: Static site Creator
Home-page: https://github.com/veryevilzed/heractor
Author: Dmitry Vysochin
Author-email: dmitry.vysochin@gmail.com
License: UNKNOWN
Platform: UNKNOWN
